icommandlib/__init__.py
icommandlib/exceptions.py
icommandlib/icommand.py
icommandlib/iprocess.py
icommandlib/messages.py
icommandlib/utils.py
icommandlib-0.8.0.dist-info/LICENSE.txt
icommandlib-0.8.0.dist-info/METADATA
icommandlib-0.8.0.dist-info/WHEEL
icommandlib-0.8.0.dist-info/top_level.txt
icommandlib-0.8.0.dist-info/RECORD
